full_adder.v
module full_adder(a, b, c, s, cy);
  input a, b, c;
  output s, cy;

  assign s = a ^ b ^ c;
  assign cy = (a & b) | (a & c) | (b & c);  // Added missing semicolon
endmodule

full_adder_tb.v
`timescale 1ns/1ps
`include "full_adder.v"
module full_adder_tb;

  // Declare inputs as reg and outputs as wire
  reg a;
  reg b;
  reg c;
  wire s;
  wire cy;

  // Instantiate the full adder module
  full_adder uut (
    .a(a),
    .b(b),
    .c(c),
    .s(s),
    .cy(cy)
  );

  // Testbench procedure
  initial begin
    // VCD file generation
    $dumpfile("full_adder.vcd");  // Specify the name of the VCD file
    $dumpvars(0, full_adder_tb);  // Dump all variables in the testbench

    // Monitor the changes in inputs and outputs
    $monitor("a = %b, b = %b, c = %b, s = %b, cy = %b", a, b, c, s, cy);
    
    // Apply all possible input combinations
    a = 0; b = 0; c = 0; #10;  // Wait for 10 time units
    a = 0; b = 0; c = 1; #10;
    a = 0; b = 1; c = 0; #10;
    a = 0; b = 1; c = 1; #10;
    a = 1; b = 0; c = 0; #10;
    a = 1; b = 0; c = 1; #10;
    a = 1; b = 1; c = 0; #10;
    a = 1; b = 1; c = 1; #10;
    
    // Finish the simulation
    $finish;
  end

endmodule

full_adder.vcd
$date
	Sat Aug 10 17:41:24 2024
$end
$version
	Icarus Verilog
$end
$timescale
	1ps
$end
$scope module full_adder_tb $end
$var wire 1 ! s $end
$var wire 1 " cy $end
$var reg 1 # a $end
$var reg 1 $ b $end
$var reg 1 % c $end
$scope module uut $end
$var wire 1 # a $end
$var wire 1 $ b $end
$var wire 1 % c $end
$var wire 1 " cy $end
$var wire 1 ! s $end
$upscope $end
$upscope $end
$enddefinitions $end
$comment Show the parameter values. $end
$dumpall
$end
#0
$dumpvars
0%
0$
0#
0"
0!
$end
#10000
1!
1%
#20000
0%
1$
#30000
1"
0!
1%
#40000
0"
1!
0%
0$
1#
#50000
1"
0!
1%
#60000
0%
1$
#70000
1!
1%
